{
    "total": [
        {
            "id": "61569711977129",
            "count": 0
        },
        {
            "id": "100077245356135",
            "count": 0
        },
        {
            "id": "100082897621667",
            "count": 20
        },
        {
            "id": "100063902783933",
            "count": 0
        },
        {
            "id": "100011296444430",
            "count": 0
        },
        {
            "id": "1247419593",
            "count": 0
        },
        {
            "id": "100080313308644",
            "count": 0
        },
        {
            "id": "100063600331393",
            "count": 0
        },
        {
            "id": "651647356",
            "count": 0
        },
        {
            "id": "61556131035355",
            "count": 6
        },
        {
            "id": "61567353704631",
            "count": 0
        },
        {
            "id": "61579289000434",
            "count": 77
        },
        {
            "id": "61579837513029",
            "count": 5
        },
        {
            "id": "100092742547112",
            "count": 0
        }
    ],
    "week": [
        {
            "id": "61569711977129",
            "count": 0
        },
        {
            "id": "100077245356135",
            "count": 0
        },
        {
            "id": "100082897621667",
            "count": 20
        },
        {
            "id": "100063902783933",
            "count": 0
        },
        {
            "id": "100011296444430",
            "count": 0
        },
        {
            "id": "1247419593",
            "count": 0
        },
        {
            "id": "100080313308644",
            "count": 0
        },
        {
            "id": "100063600331393",
            "count": 0
        },
        {
            "id": "651647356",
            "count": 0
        },
        {
            "id": "61556131035355",
            "count": 6
        },
        {
            "id": "61567353704631",
            "count": 0
        },
        {
            "id": "61579289000434",
            "count": 77
        },
        {
            "id": "61579837513029",
            "count": 5
        },
        {
            "id": "100092742547112",
            "count": 0
        }
    ],
    "day": [
        {
            "id": "61569711977129",
            "count": 0
        },
        {
            "id": "100077245356135",
            "count": 0
        },
        {
            "id": "100082897621667",
            "count": 20
        },
        {
            "id": "100063902783933",
            "count": 0
        },
        {
            "id": "100011296444430",
            "count": 0
        },
        {
            "id": "1247419593",
            "count": 0
        },
        {
            "id": "100080313308644",
            "count": 0
        },
        {
            "id": "100063600331393",
            "count": 0
        },
        {
            "id": "651647356",
            "count": 0
        },
        {
            "id": "61556131035355",
            "count": 6
        },
        {
            "id": "61567353704631",
            "count": 0
        },
        {
            "id": "61579289000434",
            "count": 77
        },
        {
            "id": "61579837513029",
            "count": 5
        },
        {
            "id": "100092742547112",
            "count": 0
        }
    ],
    "time": 1,
    "last": {
        "time": 2,
        "day": [
            {
                "id": "61569711977129",
                "count": 0
            },
            {
                "id": "100077245356135",
                "count": 0
            },
            {
                "id": "100082897621667",
                "count": 0
            },
            {
                "id": "100063902783933",
                "count": 0
            },
            {
                "id": "100011296444430",
                "count": 0
            },
            {
                "id": "1247419593",
                "count": 0
            },
            {
                "id": "100080313308644",
                "count": 0
            },
            {
                "id": "100063600331393",
                "count": 0
            },
            {
                "id": "651647356",
                "count": 0
            },
            {
                "id": "61556131035355",
                "count": 0
            },
            {
                "id": "61567353704631",
                "count": 0
            },
            {
                "id": "61579289000434",
                "count": 0
            },
            {
                "id": "61579837513029",
                "count": 0
            },
            {
                "id": "100092742547112",
                "count": 0
            }
        ],
        "week": [
            {
                "id": "61569711977129",
                "count": 0
            },
            {
                "id": "100077245356135",
                "count": 0
            },
            {
                "id": "100082897621667",
                "count": 0
            },
            {
                "id": "100063902783933",
                "count": 0
            },
            {
                "id": "100011296444430",
                "count": 0
            },
            {
                "id": "1247419593",
                "count": 0
            },
            {
                "id": "100080313308644",
                "count": 0
            },
            {
                "id": "100063600331393",
                "count": 0
            },
            {
                "id": "651647356",
                "count": 0
            },
            {
                "id": "61556131035355",
                "count": 0
            },
            {
                "id": "61567353704631",
                "count": 0
            },
            {
                "id": "61579289000434",
                "count": 0
            },
            {
                "id": "61579837513029",
                "count": 0
            },
            {
                "id": "100092742547112",
                "count": 0
            }
        ]
    }
}